odoo/addons/account_move_line_payment/README.rst
odoo/addons/account_move_line_payment/__init__.py
odoo/addons/account_move_line_payment/__manifest__.py
odoo/addons/account_move_line_payment/i18n/account_move_line_payment.pot
odoo/addons/account_move_line_payment/i18n/es.po
odoo/addons/account_move_line_payment/i18n/it.po
odoo/addons/account_move_line_payment/i18n/pt_BR.po
odoo/addons/account_move_line_payment/models/__init__.py
odoo/addons/account_move_line_payment/models/account_move_line.py
odoo/addons/account_move_line_payment/readme/CONFIGURE.md
odoo/addons/account_move_line_payment/readme/CONTEXT.md
odoo/addons/account_move_line_payment/readme/CONTRIBUTORS.md
odoo/addons/account_move_line_payment/readme/CREDITS.md
odoo/addons/account_move_line_payment/readme/DESCRIPTION.md
odoo/addons/account_move_line_payment/readme/ROADMAP.md
odoo/addons/account_move_line_payment/readme/USAGE.md
odoo/addons/account_move_line_payment/static/description/icon.png
odoo/addons/account_move_line_payment/static/description/index.html
odoo/addons/account_move_line_payment/views/account_move_line_view.xml
odoo_addon_account_move_line_payment-16.0.1.0.0.5.dist-info/METADATA
odoo_addon_account_move_line_payment-16.0.1.0.0.5.dist-info/WHEEL
odoo_addon_account_move_line_payment-16.0.1.0.0.5.dist-info/top_level.txt
odoo_addon_account_move_line_payment-16.0.1.0.0.5.dist-info/RECORD
